burltnw
