Metadata-Version: 2.1
Name: burltnw
Version: 0.2.3
Summary: module of lab robotics as use in develop application
Home-page: https://github.com/tanawatthuamthet/burltnw
Author: Tanawat
Author-email: tempkakao@gmail.com
License: tnw
Keywords: burl,robot,apollo
Platform: UNKNOWN
